tvi_footballindex/__init__.py
tvi_footballindex/parsing/__init__.py
tvi_footballindex/parsing/f24_parser.py
tvi_footballindex/tvi/__init__.py
tvi_footballindex/tvi/calculator.py
tvi_footballindex/utils/__init__.py
tvi_footballindex/utils/helpers.py
tvi_footballindex-0.3.0.dist-info/licenses/LICENSE
tvi_footballindex-0.3.0.dist-info/METADATA
tvi_footballindex-0.3.0.dist-info/WHEEL
tvi_footballindex-0.3.0.dist-info/top_level.txt
tvi_footballindex-0.3.0.dist-info/RECORD
