Metadata-Version: 2.4
Name: tvi-footballindex
Version: 0.3.0
Summary: A Python library for calculating Tactical Versatility Index (TVI) in football analytics
Author-email: Luis Doutor Simoes <luis.d.simoes@tecnico.ulisboa.pt>
License: MIT
Project-URL: Homepage, https://github.com/LuisSimoes17/TVI_footballindex
Project-URL: Repository, https://github.com/LuisSimoes17/TVI_footballindex.git
Project-URL: Issues, https://github.com/LuisSimoes17/TVI_footballindex/issues
Keywords: football,soccer,analytics,tactical,versatility,index,sports,data-analysis,tvi,f24,performance-metrics
Classifier: Development Status :: 3 - Alpha
Classifier: Intended Audience :: Developers
Classifier: Intended Audience :: Science/Research
Classifier: License :: OSI Approved :: MIT License
Classifier: Programming Language :: Python :: 3
Classifier: Programming Language :: Python :: 3.8
Classifier: Programming Language :: Python :: 3.9
Classifier: Programming Language :: Python :: 3.10
Classifier: Programming Language :: Python :: 3.11
Classifier: Programming Language :: Python :: 3.12
Classifier: Topic :: Games/Entertainment
Classifier: Topic :: Scientific/Engineering :: Information Analysis
Requires-Python: >=3.8
License-File: LICENSE
Requires-Dist: pandas>=1.3.0
Requires-Dist: numpy>=1.20.0
Requires-Dist: tqdm>=4.60.0
Provides-Extra: dev
Requires-Dist: pytest>=6.0; extra == "dev"
Requires-Dist: pytest-cov>=2.0; extra == "dev"
Requires-Dist: black>=21.0; extra == "dev"
Requires-Dist: flake8>=3.8; extra == "dev"
Requires-Dist: mypy>=0.800; extra == "dev"
Requires-Dist: jupyter>=1.0.0; extra == "dev"
Provides-Extra: docs
Requires-Dist: sphinx>=4.0; extra == "docs"
Requires-Dist: sphinx-rtd-theme>=1.0; extra == "docs"
Dynamic: license-file
